{
  "kind": "collectionType",
  "collectionName": "visitors",
  "info": {
    "singularName": "visitor",
    "pluralName": "visitors",
    "displayName": "Visitor",
    "description": "방문자 추적 정보"
  },
  "options": {
    "draftAndPublish": false
  },
  "pluginOptions": {},
  "attributes": {
    "ipAddress": {
      "type": "string",
      "required": true,
      "maxLength": 45
    },
    "userAgent": {
      "type": "text"
    },
    "referrer": {
      "type": "string"
    },
    "page": {
      "type": "string",
      "required": true
    },
    "country": {
      "type": "string"
    },
    "city": {
      "type": "string"
    },
    "visitedAt": {
      "type": "datetime",
      "required": true
    },
    "sessionId": {
      "type": "string"
    },
    "os": {
      "type": "string"
    },
    "osVersion": {
      "type": "string"
    },
    "browser": {
      "type": "string"
    },
    "browserVersion": {
      "type": "string"
    },
    "deviceType": {
      "type": "string"
    },
    "isOwnerVisit": {
      "type": "boolean",
      "default": false
    },
    "ownerTag": {
      "type": "string"
    },
    "ownerNote": {
      "type": "string"
    },
    "continent": { "type": "string" },
    "countryCode": { "type": "string", "maxLength": 2 },
    "region": { "type": "string" },
    "regionCode": { "type": "string" },
    "district": { "type": "string" },
    "latitude": { "type": "decimal" },
    "longitude": { "type": "decimal" },
    "timezone": { "type": "string" },
    "asn": { "type": "string" },
    "isp": { "type": "string" }
  }
}
